[
  {
    "lat": -9.2070755,
    "lng": -35.3341371
  },
  {
    "lat": -9.2069394,
    "lng": -35.3343845
  },
  {
    "lat": -9.2076909,
    "lng": -35.3346622
  },
  {
    "lat": -9.2084224,
    "lng": -35.3348622
  },
  {
    "lat": -9.2087997,
    "lng": -35.3349554
  },
  {
    "lat": -9.2091086,
    "lng": -35.3350081
  },
  {
    "lat": -9.2097452,
    "lng": -35.3351696
  },
  {
    "lat": -9.2100556,
    "lng": -35.3344461
  },
  {
    "lat": -9.2103351,
    "lng": -35.334235
  },
  {
    "lat": -9.2103817,
    "lng": -35.333288
  },
  {
    "lat": -9.209742,
    "lng": -35.3330396
  },
  {
    "lat": -9.209298,
    "lng": -35.3329465
  },
  {
    "lat": -9.2090838,
    "lng": -35.3328781
  },
  {
    "lat": -9.208795,
    "lng": -35.3327043
  },
  {
    "lat": -9.2082098,
    "lng": -35.3323612
  },
  {
    "lat": -9.2078977,
    "lng": -35.3322804
  },
  {
    "lat": -9.2077471,
    "lng": -35.3327912
  },
  {
    "lat": -9.2075313,
    "lng": -35.3328875
  },
  {
    "lat": -9.2072845,
    "lng": -35.3331141
  },
  {
    "lat": -9.2071076,
    "lng": -35.3334036
  },
  {
    "lat": -9.2072023,
    "lng": -35.3335093
  },
  {
    "lat": -9.2073507,
    "lng": -35.3336678
  },
  {
    "lat": -9.2072377,
    "lng": -35.3338482
  },
  {
    "lat": -9.2070755,
    "lng": -35.3341371
  }
]