[
  {
    "lat": -10.2953602,
    "lng": -36.5719469
  },
  {
    "lat": -10.2953933,
    "lng": -36.5717846
  },
  {
    "lat": -10.295545,
    "lng": -36.5712467
  },
  {
    "lat": -10.2955153,
    "lng": -36.5704677
  },
  {
    "lat": -10.2957905,
    "lng": -36.5697268
  },
  {
    "lat": -10.2962478,
    "lng": -36.5686048
  },
  {
    "lat": -10.2962689,
    "lng": -36.5682196
  },
  {
    "lat": -10.2956508,
    "lng": -36.5682069
  },
  {
    "lat": -10.2955915,
    "lng": -36.5686429
  },
  {
    "lat": -10.2954645,
    "lng": -36.5689478
  },
  {
    "lat": -10.2953121,
    "lng": -36.5692992
  },
  {
    "lat": -10.2950623,
    "lng": -36.5697818
  },
  {
    "lat": -10.294948,
    "lng": -36.5702391
  },
  {
    "lat": -10.2949607,
    "lng": -36.5706963
  },
  {
    "lat": -10.2949734,
    "lng": -36.5710943
  },
  {
    "lat": -10.2948803,
    "lng": -36.5714414
  },
  {
    "lat": -10.294868,
    "lng": -36.5717277
  },
  {
    "lat": -10.2950848,
    "lng": -36.5718533
  },
  {
    "lat": -10.2951816,
    "lng": -36.571889
  },
  {
    "lat": -10.2952475,
    "lng": -36.5719076
  },
  {
    "lat": -10.2953602,
    "lng": -36.5719469
  }
]