[
  {
    "lat": -9.619148,
    "lng": -35.7581473
  },
  {
    "lat": -9.6189734,
    "lng": -35.7583293
  },
  {
    "lat": -9.6189236,
    "lng": -35.7582678
  },
  {
    "lat": -9.6186334,
    "lng": -35.7579079
  },
  {
    "lat": -9.6186132,
    "lng": -35.7578837
  },
  {
    "lat": -9.6180301,
    "lng": -35.7571653
  },
  {
    "lat": -9.6179675,
    "lng": -35.7570944
  },
  {
    "lat": -9.6178371,
    "lng": -35.756929
  },
  {
    "lat": -9.6177425,
    "lng": -35.756809
  },
  {
    "lat": -9.6177346,
    "lng": -35.7567917
  },
  {
    "lat": -9.6177293,
    "lng": -35.7567802
  },
  {
    "lat": -9.6176787,
    "lng": -35.756711
  },
  {
    "lat": -9.6176366,
    "lng": -35.7566406
  },
  {
    "lat": -9.6175212,
    "lng": -35.7565178
  },
  {
    "lat": -9.6174555,
    "lng": -35.7564376
  },
  {
    "lat": -9.6173966,
    "lng": -35.7564901
  },
  {
    "lat": -9.6173585,
    "lng": -35.7565324
  },
  {
    "lat": -9.6172751,
    "lng": -35.7566368
  },
  {
    "lat": -9.6170007,
    "lng": -35.7570321
  },
  {
    "lat": -9.6168881,
    "lng": -35.7571972
  },
  {
    "lat": -9.6168822,
    "lng": -35.7572063
  },
  {
    "lat": -9.6168483,
    "lng": -35.7572586
  },
  {
    "lat": -9.6168435,
    "lng": -35.7572676
  },
  {
    "lat": -9.6168212,
    "lng": -35.7573091
  },
  {
    "lat": -9.6168206,
    "lng": -35.7573102
  },
  {
    "lat": -9.6168024,
    "lng": -35.7573413
  },
  {
    "lat": -9.6167765,
    "lng": -35.7573756
  },
  {
    "lat": -9.6167845,
    "lng": -35.7573905
  },
  {
    "lat": -9.6167902,
    "lng": -35.7574089
  },
  {
    "lat": -9.6167957,
    "lng": -35.7574409
  },
  {
    "lat": -9.6168044,
    "lng": -35.7574696
  },
  {
    "lat": -9.6169417,
    "lng": -35.7578966
  },
  {
    "lat": -9.6171455,
    "lng": -35.7585219
  },
  {
    "lat": -9.6173329,
    "lng": -35.7590929
  },
  {
    "lat": -9.6175175,
    "lng": -35.7596281
  },
  {
    "lat": -9.6175674,
    "lng": -35.7597443
  },
  {
    "lat": -9.6175925,
    "lng": -35.7597908
  },
  {
    "lat": -9.6176352,
    "lng": -35.7598589
  },
  {
    "lat": -9.617742,
    "lng": -35.7599794
  },
  {
    "lat": -9.6175887,
    "lng": -35.7602081
  },
  {
    "lat": -9.61747,
    "lng": -35.7601167
  },
  {
    "lat": -9.6174629,
    "lng": -35.7600742
  },
  {
    "lat": -9.6174063,
    "lng": -35.7600176
  },
  {
    "lat": -9.6164532,
    "lng": -35.7595529
  },
  {
    "lat": -9.6163942,
    "lng": -35.7595505
  },
  {
    "lat": -9.6162999,
    "lng": -35.759508
  },
  {
    "lat": -9.6161324,
    "lng": -35.7594939
  },
  {
    "lat": -9.6159437,
    "lng": -35.7594302
  },
  {
    "lat": -9.6158304,
    "lng": -35.7596142
  },
  {
    "lat": -9.6159036,
    "lng": -35.7599893
  },
  {
    "lat": -9.6160451,
    "lng": -35.7601497
  },
  {
    "lat": -9.6163707,
    "lng": -35.7603549
  },
  {
    "lat": -9.6164863,
    "lng": -35.7605272
  },
  {
    "lat": -9.6167481,
    "lng": -35.760815
  },
  {
    "lat": -9.6169189,
    "lng": -35.7609163
  },
  {
    "lat": -9.6170426,
    "lng": -35.7610225
  },
  {
    "lat": -9.617167,
    "lng": -35.7611292
  },
  {
    "lat": -9.6174792,
    "lng": -35.7606862
  },
  {
    "lat": -9.6178754,
    "lng": -35.7601242
  },
  {
    "lat": -9.6182003,
    "lng": -35.7596686
  },
  {
    "lat": -9.6183222,
    "lng": -35.7594676
  },
  {
    "lat": -9.6187837,
    "lng": -35.7597174
  },
  {
    "lat": -9.6188988,
    "lng": -35.7595261
  },
  {
    "lat": -9.6191047,
    "lng": -35.7596442
  },
  {
    "lat": -9.6191412,
    "lng": -35.7595941
  },
  {
    "lat": -9.6197453,
    "lng": -35.7599327
  },
  {
    "lat": -9.6198987,
    "lng": -35.7596609
  },
  {
    "lat": -9.6200647,
    "lng": -35.7593586
  },
  {
    "lat": -9.620261,
    "lng": -35.7589933
  },
  {
    "lat": -9.6199724,
    "lng": -35.7587687
  },
  {
    "lat": -9.6196231,
    "lng": -35.758455
  },
  {
    "lat": -9.619148,
    "lng": -35.7581473
  }
]