[
  {
    "lat": -9.6390628,
    "lng": -35.7221236
  },
  {
    "lat": -9.6390709,
    "lng": -35.7221295
  },
  {
    "lat": -9.6390666,
    "lng": -35.7221721
  },
  {
    "lat": -9.6390665,
    "lng": -35.722173
  },
  {
    "lat": -9.6390747,
    "lng": -35.7222893
  },
  {
    "lat": -9.6390463,
    "lng": -35.7223726
  },
  {
    "lat": -9.6390237,
    "lng": -35.7227329
  },
  {
    "lat": -9.6390321,
    "lng": -35.7227487
  },
  {
    "lat": -9.6390329,
    "lng": -35.7227592
  },
  {
    "lat": -9.6390336,
    "lng": -35.7227767
  },
  {
    "lat": -9.6390321,
    "lng": -35.7227803
  },
  {
    "lat": -9.6390356,
    "lng": -35.7228683
  },
  {
    "lat": -9.6390676,
    "lng": -35.7229342
  },
  {
    "lat": -9.6390699,
    "lng": -35.722943
  },
  {
    "lat": -9.639081,
    "lng": -35.7229852
  },
  {
    "lat": -9.6390813,
    "lng": -35.7229865
  },
  {
    "lat": -9.6390909,
    "lng": -35.7230217
  },
  {
    "lat": -9.6390957,
    "lng": -35.7230394
  },
  {
    "lat": -9.6391136,
    "lng": -35.7230878
  },
  {
    "lat": -9.6392475,
    "lng": -35.7232817
  },
  {
    "lat": -9.6392736,
    "lng": -35.7233179
  },
  {
    "lat": -9.6392865,
    "lng": -35.7233359
  },
  {
    "lat": -9.6393083,
    "lng": -35.7233121
  },
  {
    "lat": -9.6393458,
    "lng": -35.7232592
  },
  {
    "lat": -9.6393594,
    "lng": -35.72324
  },
  {
    "lat": -9.6392901,
    "lng": -35.7232113
  },
  {
    "lat": -9.6392356,
    "lng": -35.7230408
  },
  {
    "lat": -9.6393195,
    "lng": -35.7229667
  },
  {
    "lat": -9.6393121,
    "lng": -35.7229153
  },
  {
    "lat": -9.6392037,
    "lng": -35.7229165
  },
  {
    "lat": -9.639205,
    "lng": -35.722821
  },
  {
    "lat": -9.6393106,
    "lng": -35.7227844
  },
  {
    "lat": -9.6393565,
    "lng": -35.7227287
  },
  {
    "lat": -9.6394643,
    "lng": -35.7227177
  },
  {
    "lat": -9.6394563,
    "lng": -35.722692
  },
  {
    "lat": -9.6392958,
    "lng": -35.7226818
  },
  {
    "lat": -9.6392958,
    "lng": -35.7227077
  },
  {
    "lat": -9.6392054,
    "lng": -35.7227097
  },
  {
    "lat": -9.6392069,
    "lng": -35.7225708
  },
  {
    "lat": -9.6392089,
    "lng": -35.7225493
  },
  {
    "lat": -9.639411,
    "lng": -35.7225763
  },
  {
    "lat": -9.6394245,
    "lng": -35.7224165
  },
  {
    "lat": -9.6394566,
    "lng": -35.7223967
  },
  {
    "lat": -9.6394532,
    "lng": -35.72234
  },
  {
    "lat": -9.6394238,
    "lng": -35.7223194
  },
  {
    "lat": -9.6394403,
    "lng": -35.7222716
  },
  {
    "lat": -9.639493,
    "lng": -35.7222561
  },
  {
    "lat": -9.6394927,
    "lng": -35.7222508
  },
  {
    "lat": -9.6397501,
    "lng": -35.7222543
  },
  {
    "lat": -9.6397477,
    "lng": -35.7221829
  },
  {
    "lat": -9.6397383,
    "lng": -35.7218874
  },
  {
    "lat": -9.6396168,
    "lng": -35.7218725
  },
  {
    "lat": -9.639587,
    "lng": -35.7216021
  },
  {
    "lat": -9.6395588,
    "lng": -35.721555
  },
  {
    "lat": -9.63952,
    "lng": -35.7214443
  },
  {
    "lat": -9.6394937,
    "lng": -35.7214365
  },
  {
    "lat": -9.6394179,
    "lng": -35.7214368
  },
  {
    "lat": -9.6393352,
    "lng": -35.7214606
  },
  {
    "lat": -9.6392575,
    "lng": -35.7215401
  },
  {
    "lat": -9.6392551,
    "lng": -35.7219987
  },
  {
    "lat": -9.6391164,
    "lng": -35.7220135
  },
  {
    "lat": -9.6390705,
    "lng": -35.7220907
  },
  {
    "lat": -9.6390628,
    "lng": -35.7221236
  }
]