[
  {
    "lat": -9.6410555,
    "lng": -35.7149221
  },
  {
    "lat": -9.6410391,
    "lng": -35.7151831
  },
  {
    "lat": -9.6410321,
    "lng": -35.7152964
  },
  {
    "lat": -9.6410282,
    "lng": -35.7153902
  },
  {
    "lat": -9.6410196,
    "lng": -35.7156232
  },
  {
    "lat": -9.6410157,
    "lng": -35.7157686
  },
  {
    "lat": -9.6410133,
    "lng": -35.7160328
  },
  {
    "lat": -9.6410086,
    "lng": -35.7162821
  },
  {
    "lat": -9.6410102,
    "lng": -35.7163392
  },
  {
    "lat": -9.6410157,
    "lng": -35.7165823
  },
  {
    "lat": -9.641033,
    "lng": -35.7170446
  },
  {
    "lat": -9.6410787,
    "lng": -35.7170465
  },
  {
    "lat": -9.6411269,
    "lng": -35.7170528
  },
  {
    "lat": -9.6414996,
    "lng": -35.7170979
  },
  {
    "lat": -9.6416062,
    "lng": -35.7171078
  },
  {
    "lat": -9.64164,
    "lng": -35.716097
  },
  {
    "lat": -9.6420332,
    "lng": -35.7160801
  },
  {
    "lat": -9.6421149,
    "lng": -35.7160322
  },
  {
    "lat": -9.642303,
    "lng": -35.7154185
  },
  {
    "lat": -9.6418955,
    "lng": -35.7153719
  },
  {
    "lat": -9.6419048,
    "lng": -35.7152107
  },
  {
    "lat": -9.6419075,
    "lng": -35.7151852
  },
  {
    "lat": -9.6419101,
    "lng": -35.7151497
  },
  {
    "lat": -9.6419194,
    "lng": -35.7150835
  },
  {
    "lat": -9.6419267,
    "lng": -35.7150305
  },
  {
    "lat": -9.6413186,
    "lng": -35.7149845
  },
  {
    "lat": -9.6410555,
    "lng": -35.7149221
  }
]