[
  {
    "lat": -9.6442973,
    "lng": -35.7239385
  },
  {
    "lat": -9.6442919,
    "lng": -35.7239402
  },
  {
    "lat": -9.6442859,
    "lng": -35.7239447
  },
  {
    "lat": -9.6442812,
    "lng": -35.7239483
  },
  {
    "lat": -9.6442773,
    "lng": -35.723955
  },
  {
    "lat": -9.6442441,
    "lng": -35.7238392
  },
  {
    "lat": -9.6442493,
    "lng": -35.7236387
  },
  {
    "lat": -9.6442887,
    "lng": -35.7235157
  },
  {
    "lat": -9.6443373,
    "lng": -35.7234756
  },
  {
    "lat": -9.6443044,
    "lng": -35.7233495
  },
  {
    "lat": -9.6442678,
    "lng": -35.7233397
  },
  {
    "lat": -9.6440816,
    "lng": -35.7232544
  },
  {
    "lat": -9.6440435,
    "lng": -35.7232365
  },
  {
    "lat": -9.6439582,
    "lng": -35.7231944
  },
  {
    "lat": -9.643906,
    "lng": -35.7233058
  },
  {
    "lat": -9.6438732,
    "lng": -35.7233728
  },
  {
    "lat": -9.6438499,
    "lng": -35.7234133
  },
  {
    "lat": -9.6438358,
    "lng": -35.7234437
  },
  {
    "lat": -9.6437914,
    "lng": -35.7235263
  },
  {
    "lat": -9.6433988,
    "lng": -35.7233261
  },
  {
    "lat": -9.6433171,
    "lng": -35.7235008
  },
  {
    "lat": -9.6433141,
    "lng": -35.7235073
  },
  {
    "lat": -9.6433104,
    "lng": -35.7235153
  },
  {
    "lat": -9.6432975,
    "lng": -35.7235431
  },
  {
    "lat": -9.6433783,
    "lng": -35.7235875
  },
  {
    "lat": -9.6433671,
    "lng": -35.7236121
  },
  {
    "lat": -9.6433636,
    "lng": -35.72362
  },
  {
    "lat": -9.6433466,
    "lng": -35.7236576
  },
  {
    "lat": -9.643297,
    "lng": -35.7237671
  },
  {
    "lat": -9.6432832,
    "lng": -35.7237978
  },
  {
    "lat": -9.6431655,
    "lng": -35.7237283
  },
  {
    "lat": -9.6431587,
    "lng": -35.723743
  },
  {
    "lat": -9.6431537,
    "lng": -35.7237538
  },
  {
    "lat": -9.6431365,
    "lng": -35.7237913
  },
  {
    "lat": -9.6431255,
    "lng": -35.7238151
  },
  {
    "lat": -9.6431672,
    "lng": -35.7238668
  },
  {
    "lat": -9.6431923,
    "lng": -35.7239317
  },
  {
    "lat": -9.6431923,
    "lng": -35.7240262
  },
  {
    "lat": -9.643193,
    "lng": -35.7240759
  },
  {
    "lat": -9.643193,
    "lng": -35.724077
  },
  {
    "lat": -9.6431483,
    "lng": -35.7240538
  },
  {
    "lat": -9.6430177,
    "lng": -35.7240771
  },
  {
    "lat": -9.6426577,
    "lng": -35.7240836
  },
  {
    "lat": -9.6426421,
    "lng": -35.724485
  },
  {
    "lat": -9.6426405,
    "lng": -35.7245278
  },
  {
    "lat": -9.6425045,
    "lng": -35.7245364
  },
  {
    "lat": -9.6424963,
    "lng": -35.7245368
  },
  {
    "lat": -9.6424945,
    "lng": -35.7245674
  },
  {
    "lat": -9.6424817,
    "lng": -35.7249535
  },
  {
    "lat": -9.6424368,
    "lng": -35.7249917
  },
  {
    "lat": -9.6424226,
    "lng": -35.725042
  },
  {
    "lat": -9.6424226,
    "lng": -35.7250825
  },
  {
    "lat": -9.6424357,
    "lng": -35.7251344
  },
  {
    "lat": -9.6424625,
    "lng": -35.7251793
  },
  {
    "lat": -9.6425771,
    "lng": -35.7252725
  },
  {
    "lat": -9.642577,
    "lng": -35.725273
  },
  {
    "lat": -9.6425847,
    "lng": -35.725279
  },
  {
    "lat": -9.6425971,
    "lng": -35.7253076
  },
  {
    "lat": -9.6425668,
    "lng": -35.7254281
  },
  {
    "lat": -9.6425664,
    "lng": -35.7254343
  },
  {
    "lat": -9.6425263,
    "lng": -35.7255881
  },
  {
    "lat": -9.6425548,
    "lng": -35.7255918
  },
  {
    "lat": -9.6425546,
    "lng": -35.725593
  },
  {
    "lat": -9.6425941,
    "lng": -35.7255815
  },
  {
    "lat": -9.6426162,
    "lng": -35.7255859
  },
  {
    "lat": -9.6426163,
    "lng": -35.7255872
  },
  {
    "lat": -9.6426174,
    "lng": -35.7256195
  },
  {
    "lat": -9.642598,
    "lng": -35.7256598
  },
  {
    "lat": -9.6425751,
    "lng": -35.7257619
  },
  {
    "lat": -9.6425469,
    "lng": -35.7257537
  },
  {
    "lat": -9.6425083,
    "lng": -35.7259129
  },
  {
    "lat": -9.6425538,
    "lng": -35.725928
  },
  {
    "lat": -9.6425397,
    "lng": -35.7259719
  },
  {
    "lat": -9.6425412,
    "lng": -35.7259724
  },
  {
    "lat": -9.6425352,
    "lng": -35.7259902
  },
  {
    "lat": -9.6424574,
    "lng": -35.7259652
  },
  {
    "lat": -9.6424418,
    "lng": -35.7260121
  },
  {
    "lat": -9.6424802,
    "lng": -35.7260279
  },
  {
    "lat": -9.6424661,
    "lng": -35.7260787
  },
  {
    "lat": -9.6424469,
    "lng": -35.7260719
  },
  {
    "lat": -9.6424309,
    "lng": -35.7261368
  },
  {
    "lat": -9.6424221,
    "lng": -35.7261339
  },
  {
    "lat": -9.6423574,
    "lng": -35.7263863
  },
  {
    "lat": -9.6424328,
    "lng": -35.726394
  },
  {
    "lat": -9.6423837,
    "lng": -35.7266255
  },
  {
    "lat": -9.6423419,
    "lng": -35.7267509
  },
  {
    "lat": -9.6422967,
    "lng": -35.7267324
  },
  {
    "lat": -9.6422301,
    "lng": -35.7268803
  },
  {
    "lat": -9.6422986,
    "lng": -35.7269065
  },
  {
    "lat": -9.6422789,
    "lng": -35.7269644
  },
  {
    "lat": -9.6422028,
    "lng": -35.7269337
  },
  {
    "lat": -9.6421557,
    "lng": -35.7270691
  },
  {
    "lat": -9.6422016,
    "lng": -35.7270884
  },
  {
    "lat": -9.6421933,
    "lng": -35.7271457
  },
  {
    "lat": -9.6421622,
    "lng": -35.7271516
  },
  {
    "lat": -9.6420825,
    "lng": -35.7271198
  },
  {
    "lat": -9.6420533,
    "lng": -35.7271092
  },
  {
    "lat": -9.6420299,
    "lng": -35.7271781
  },
  {
    "lat": -9.6420271,
    "lng": -35.7271861
  },
  {
    "lat": -9.6419887,
    "lng": -35.7273192
  },
  {
    "lat": -9.6419368,
    "lng": -35.7273049
  },
  {
    "lat": -9.6419219,
    "lng": -35.7273328
  },
  {
    "lat": -9.6418506,
    "lng": -35.7272998
  },
  {
    "lat": -9.6418701,
    "lng": -35.7272446
  },
  {
    "lat": -9.6418331,
    "lng": -35.7272317
  },
  {
    "lat": -9.6417834,
    "lng": -35.7273663
  },
  {
    "lat": -9.6416994,
    "lng": -35.727332
  },
  {
    "lat": -9.6416898,
    "lng": -35.7273718
  },
  {
    "lat": -9.6415526,
    "lng": -35.7277873
  },
  {
    "lat": -9.6416213,
    "lng": -35.7277856
  },
  {
    "lat": -9.6416844,
    "lng": -35.7278025
  },
  {
    "lat": -9.6417286,
    "lng": -35.7278138
  },
  {
    "lat": -9.6417813,
    "lng": -35.7278925
  },
  {
    "lat": -9.6418363,
    "lng": -35.7279103
  },
  {
    "lat": -9.6419112,
    "lng": -35.7279136
  },
  {
    "lat": -9.641988,
    "lng": -35.7279197
  },
  {
    "lat": -9.6420187,
    "lng": -35.7279208
  },
  {
    "lat": -9.6420448,
    "lng": -35.7279302
  },
  {
    "lat": -9.6420881,
    "lng": -35.7279451
  },
  {
    "lat": -9.6421394,
    "lng": -35.7279664
  },
  {
    "lat": -9.6421657,
    "lng": -35.7279512
  },
  {
    "lat": -9.6421905,
    "lng": -35.7279013
  },
  {
    "lat": -9.6422088,
    "lng": -35.7278659
  },
  {
    "lat": -9.6422289,
    "lng": -35.7278433
  },
  {
    "lat": -9.6422445,
    "lng": -35.7278161
  },
  {
    "lat": -9.6422682,
    "lng": -35.7277854
  },
  {
    "lat": -9.6423271,
    "lng": -35.7277603
  },
  {
    "lat": -9.6423527,
    "lng": -35.7277269
  },
  {
    "lat": -9.6423691,
    "lng": -35.7277042
  },
  {
    "lat": -9.6423984,
    "lng": -35.7276635
  },
  {
    "lat": -9.6424221,
    "lng": -35.7276364
  },
  {
    "lat": -9.6424458,
    "lng": -35.7276129
  },
  {
    "lat": -9.6424703,
    "lng": -35.7275949
  },
  {
    "lat": -9.6424966,
    "lng": -35.7275778
  },
  {
    "lat": -9.6425223,
    "lng": -35.7275727
  },
  {
    "lat": -9.642535,
    "lng": -35.7275726
  },
  {
    "lat": -9.6425834,
    "lng": -35.7275721
  },
  {
    "lat": -9.6426286,
    "lng": -35.7275725
  },
  {
    "lat": -9.6426712,
    "lng": -35.7275592
  },
  {
    "lat": -9.6427003,
    "lng": -35.7275257
  },
  {
    "lat": -9.6427214,
    "lng": -35.7274867
  },
  {
    "lat": -9.6427271,
    "lng": -35.7274549
  },
  {
    "lat": -9.6427382,
    "lng": -35.7274268
  },
  {
    "lat": -9.6427529,
    "lng": -35.727395
  },
  {
    "lat": -9.6427666,
    "lng": -35.7273696
  },
  {
    "lat": -9.6427804,
    "lng": -35.7273397
  },
  {
    "lat": -9.6427923,
    "lng": -35.7273179
  },
  {
    "lat": -9.6428116,
    "lng": -35.7272826
  },
  {
    "lat": -9.6428299,
    "lng": -35.7272518
  },
  {
    "lat": -9.6428509,
    "lng": -35.7272256
  },
  {
    "lat": -9.6428738,
    "lng": -35.7271866
  },
  {
    "lat": -9.6428907,
    "lng": -35.7271558
  },
  {
    "lat": -9.6429076,
    "lng": -35.7271368
  },
  {
    "lat": -9.642934,
    "lng": -35.7271124
  },
  {
    "lat": -9.6429568,
    "lng": -35.727088
  },
  {
    "lat": -9.6429715,
    "lng": -35.7270608
  },
  {
    "lat": -9.6429889,
    "lng": -35.7270309
  },
  {
    "lat": -9.6430009,
    "lng": -35.7269946
  },
  {
    "lat": -9.6430092,
    "lng": -35.7269673
  },
  {
    "lat": -9.6430122,
    "lng": -35.7269373
  },
  {
    "lat": -9.6430179,
    "lng": -35.7269018
  },
  {
    "lat": -9.6430172,
    "lng": -35.7268709
  },
  {
    "lat": -9.643003,
    "lng": -35.7268362
  },
  {
    "lat": -9.6429873,
    "lng": -35.7268037
  },
  {
    "lat": -9.6429745,
    "lng": -35.726784
  },
  {
    "lat": -9.6429486,
    "lng": -35.7267574
  },
  {
    "lat": -9.6429261,
    "lng": -35.7267354
  },
  {
    "lat": -9.6429056,
    "lng": -35.7267079
  },
  {
    "lat": -9.6428886,
    "lng": -35.7266796
  },
  {
    "lat": -9.6428789,
    "lng": -35.7266476
  },
  {
    "lat": -9.6428774,
    "lng": -35.7266185
  },
  {
    "lat": -9.6428767,
    "lng": -35.7265867
  },
  {
    "lat": -9.6428824,
    "lng": -35.7265548
  },
  {
    "lat": -9.6429011,
    "lng": -35.7265309
  },
  {
    "lat": -9.6429146,
    "lng": -35.7265045
  },
  {
    "lat": -9.6429209,
    "lng": -35.7264696
  },
  {
    "lat": -9.6429219,
    "lng": -35.726432
  },
  {
    "lat": -9.6429191,
    "lng": -35.7264128
  },
  {
    "lat": -9.642909,
    "lng": -35.7263773
  },
  {
    "lat": -9.6428982,
    "lng": -35.7263504
  },
  {
    "lat": -9.6428764,
    "lng": -35.7263035
  },
  {
    "lat": -9.6428506,
    "lng": -35.726266
  },
  {
    "lat": -9.6428307,
    "lng": -35.7262321
  },
  {
    "lat": -9.6428128,
    "lng": -35.7261774
  },
  {
    "lat": -9.6428279,
    "lng": -35.7261239
  },
  {
    "lat": -9.6428796,
    "lng": -35.7260929
  },
  {
    "lat": -9.6429093,
    "lng": -35.7260861
  },
  {
    "lat": -9.6429589,
    "lng": -35.7260936
  },
  {
    "lat": -9.6429893,
    "lng": -35.7260661
  },
  {
    "lat": -9.6430177,
    "lng": -35.726016
  },
  {
    "lat": -9.6430351,
    "lng": -35.7259936
  },
  {
    "lat": -9.6430785,
    "lng": -35.725946
  },
  {
    "lat": -9.6430941,
    "lng": -35.7259182
  },
  {
    "lat": -9.6431042,
    "lng": -35.7258877
  },
  {
    "lat": -9.6431283,
    "lng": -35.7258399
  },
  {
    "lat": -9.6431452,
    "lng": -35.7258011
  },
  {
    "lat": -9.6431677,
    "lng": -35.7257672
  },
  {
    "lat": -9.6432014,
    "lng": -35.7257227
  },
  {
    "lat": -9.6432064,
    "lng": -35.7258017
  },
  {
    "lat": -9.6432045,
    "lng": -35.7258068
  },
  {
    "lat": -9.6431745,
    "lng": -35.7258862
  },
  {
    "lat": -9.6431552,
    "lng": -35.7260041
  },
  {
    "lat": -9.6431481,
    "lng": -35.7260688
  },
  {
    "lat": -9.6431469,
    "lng": -35.7261283
  },
  {
    "lat": -9.6431522,
    "lng": -35.7263606
  },
  {
    "lat": -9.6431568,
    "lng": -35.7265521
  },
  {
    "lat": -9.6433117,
    "lng": -35.7265381
  },
  {
    "lat": -9.6432932,
    "lng": -35.7267137
  },
  {
    "lat": -9.6433114,
    "lng": -35.7267707
  },
  {
    "lat": -9.6433323,
    "lng": -35.7267984
  },
  {
    "lat": -9.6433345,
    "lng": -35.7268406
  },
  {
    "lat": -9.6433704,
    "lng": -35.7269412
  },
  {
    "lat": -9.6434172,
    "lng": -35.727137
  },
  {
    "lat": -9.6434393,
    "lng": -35.7271441
  },
  {
    "lat": -9.6434563,
    "lng": -35.727103
  },
  {
    "lat": -9.6435005,
    "lng": -35.727089
  },
  {
    "lat": -9.6436479,
    "lng": -35.7270618
  },
  {
    "lat": -9.643864,
    "lng": -35.7270351
  },
  {
    "lat": -9.6440576,
    "lng": -35.7270186
  },
  {
    "lat": -9.6443887,
    "lng": -35.7269958
  },
  {
    "lat": -9.6443849,
    "lng": -35.7262407
  },
  {
    "lat": -9.6436485,
    "lng": -35.7262243
  },
  {
    "lat": -9.643642,
    "lng": -35.7261451
  },
  {
    "lat": -9.6436459,
    "lng": -35.7260432
  },
  {
    "lat": -9.6436672,
    "lng": -35.7258084
  },
  {
    "lat": -9.6436775,
    "lng": -35.725747
  },
  {
    "lat": -9.6437192,
    "lng": -35.7257196
  },
  {
    "lat": -9.6440691,
    "lng": -35.7255921
  },
  {
    "lat": -9.6443976,
    "lng": -35.7254935
  },
  {
    "lat": -9.6444487,
    "lng": -35.7254776
  },
  {
    "lat": -9.6444532,
    "lng": -35.7250684
  },
  {
    "lat": -9.6444681,
    "lng": -35.7250587
  },
  {
    "lat": -9.6445115,
    "lng": -35.7250363
  },
  {
    "lat": -9.6448543,
    "lng": -35.7248536
  },
  {
    "lat": -9.6449971,
    "lng": -35.7248032
  },
  {
    "lat": -9.6450963,
    "lng": -35.7247815
  },
  {
    "lat": -9.6451071,
    "lng": -35.7241848
  },
  {
    "lat": -9.6450881,
    "lng": -35.7241803
  },
  {
    "lat": -9.6450601,
    "lng": -35.7241558
  },
  {
    "lat": -9.6450334,
    "lng": -35.724094
  },
  {
    "lat": -9.6449826,
    "lng": -35.7239803
  },
  {
    "lat": -9.6449535,
    "lng": -35.7239018
  },
  {
    "lat": -9.6448806,
    "lng": -35.7239154
  },
  {
    "lat": -9.6447917,
    "lng": -35.7239103
  },
  {
    "lat": -9.644754,
    "lng": -35.7239049
  },
  {
    "lat": -9.6447074,
    "lng": -35.723896
  },
  {
    "lat": -9.6446773,
    "lng": -35.723892
  },
  {
    "lat": -9.644638,
    "lng": -35.7238906
  },
  {
    "lat": -9.6446108,
    "lng": -35.7238961
  },
  {
    "lat": -9.6445849,
    "lng": -35.7239055
  },
  {
    "lat": -9.6445514,
    "lng": -35.7239148
  },
  {
    "lat": -9.6444955,
    "lng": -35.723943
  },
  {
    "lat": -9.644467,
    "lng": -35.7239613
  },
  {
    "lat": -9.6444352,
    "lng": -35.7239732
  },
  {
    "lat": -9.6443809,
    "lng": -35.7239571
  },
  {
    "lat": -9.6442973,
    "lng": -35.7239385
  }
]